hmd_cli_neuronsphere/__init__.py
hmd_cli_neuronsphere/controller.py
hmd_cli_neuronsphere/hmd_cli_neuronsphere.py
hmd_cli_neuronsphere/plugins/__init__.py
hmd_cli_neuronsphere/plugins/airflow.py
hmd_cli_neuronsphere/plugins/apache_superset.py
hmd_cli_neuronsphere/plugins/dynamodb.py
hmd_cli_neuronsphere/plugins/graph.py
hmd_cli_neuronsphere/plugins/jupyter.py
hmd_cli_neuronsphere/plugins/main.py
hmd_cli_neuronsphere/plugins/minio.py
hmd_cli_neuronsphere/plugins/telemetry.py
hmd_cli_neuronsphere/plugins/transform.py
hmd_cli_neuronsphere/plugins/trino.py
hmd_cli_neuronsphere/services/docker-compose.airflow.yml
hmd_cli_neuronsphere/services/docker-compose.apache-superset.yml
hmd_cli_neuronsphere/services/docker-compose.datadog.yml
hmd_cli_neuronsphere/services/docker-compose.dynamodb.yml
hmd_cli_neuronsphere/services/docker-compose.graph.yml
hmd_cli_neuronsphere/services/docker-compose.jupyter.yml
hmd_cli_neuronsphere/services/docker-compose.main.yml
hmd_cli_neuronsphere/services/docker-compose.minio.yml
hmd_cli_neuronsphere/services/docker-compose.telemetry.yml
hmd_cli_neuronsphere/services/docker-compose.transform.yml
hmd_cli_neuronsphere/services/docker-compose.trino.yml
hmd_cli_neuronsphere/services/hadoop-hive.env
hmd_cli_neuronsphere/services/hadoop/capacity-scheduler.xml
hmd_cli_neuronsphere/services/hadoop/configuration.xsl
hmd_cli_neuronsphere/services/hadoop/container-executor.cfg
hmd_cli_neuronsphere/services/hadoop/core-site.xml
hmd_cli_neuronsphere/services/hadoop/hadoop-env.cmd
hmd_cli_neuronsphere/services/hadoop/hadoop-env.sh
hmd_cli_neuronsphere/services/hadoop/hadoop-metrics.properties
hmd_cli_neuronsphere/services/hadoop/hadoop-metrics2.properties
hmd_cli_neuronsphere/services/hadoop/hadoop-policy.xml
hmd_cli_neuronsphere/services/hadoop/hdfs-site.xml
hmd_cli_neuronsphere/services/hadoop/httpfs-env.sh
hmd_cli_neuronsphere/services/hadoop/httpfs-log4j.properties
hmd_cli_neuronsphere/services/hadoop/httpfs-signature.secret
hmd_cli_neuronsphere-0.3.160.dist-info/METADATA
hmd_cli_neuronsphere-0.3.160.dist-info/WHEEL
hmd_cli_neuronsphere-0.3.160.dist-info/entry_points.txt
hmd_cli_neuronsphere-0.3.160.dist-info/top_level.txt
hmd_cli_neuronsphere-0.3.160.dist-info/RECORD
